networking_ansible/__init__.py
networking_ansible/config.py
networking_ansible/constants.py
networking_ansible/exceptions.py
networking_ansible/ml2/__init__.py
networking_ansible/ml2/mech_driver.py
networking_ansible/ml2/trunk_driver.py
networking_ansible/tests/__init__.py
networking_ansible/tests/unit/__init__.py
networking_ansible/tests/unit/base.py
networking_ansible/tests/unit/test_config.py
networking_ansible/tests/unit/ml2/__init__.py
networking_ansible/tests/unit/ml2/test_mech_driver.py
networking_ansible/tests/unit/ml2/test_trunk_driver.py
networking_ansible-5.0.0.data/data/etc/neutron/plugins/ml2/ml2_conf_ansible.ini.sample
networking_ansible-5.0.0.dist-info/DESCRIPTION.rst
networking_ansible-5.0.0.dist-info/METADATA
networking_ansible-5.0.0.dist-info/RECORD
networking_ansible-5.0.0.dist-info/WHEEL
networking_ansible-5.0.0.dist-info/entry_points.txt
networking_ansible-5.0.0.dist-info/metadata.json
networking_ansible-5.0.0.dist-info/pbr.json
networking_ansible-5.0.0.dist-info/top_level.txt
