Metadata-Version: 2.0
Name: networking-ansible
Version: 5.0.0
Summary: Ansible Networking ML2 Driver
Home-page: https://opendev.org/openstack/networking-ansible
Author: OpenStack
Author-email: openstack-discuss@lists.openstack.org
License: UNKNOWN
Platform: UNKNOWN
Classifier: Environment :: OpenStack
Classifier: Intended Audience :: Information Technology
Classifier: Intended Audience :: System Administrators
Classifier: License :: OSI Approved :: Apache Software License
Classifier: Operating System :: POSIX :: Linux
Classifier: Programming Language :: Python
Classifier: Programming Language :: Python :: 2
Classifier: Programming Language :: Python :: 2.7
Classifier: Programming Language :: Python :: 3
Classifier: Programming Language :: Python :: 3.5
Classifier: Programming Language :: Python :: 3.8
Requires-Dist: ansible-runner (>=1.0.5)
Requires-Dist: debtcollector (>=1.21.0)
Requires-Dist: network-runner (>=0.2.2)
Requires-Dist: neutron-lib (>=2.4.0)
Requires-Dist: neutron (>=16.0.0.0)
Requires-Dist: pbr (>=2.0)
Requires-Dist: tooz (>=1.28.0)
